ycv/__init__.py
ycv/build_materials_cli.py
ycv/publications.py
ycv/yamlToTex.py
ycv-0.0.26.dist-info/licenses/LICENSE
ycv-0.0.26.dist-info/METADATA
ycv-0.0.26.dist-info/WHEEL
ycv-0.0.26.dist-info/entry_points.txt
ycv-0.0.26.dist-info/top_level.txt
ycv-0.0.26.dist-info/RECORD
