Metadata-Version: 2.4
Name: ycv
Version: 0.0.26
Summary: Build CV and job application materials from yaml files
Home-page: https://github.com/md-arif-shaikh/ycv
Author: Md Arif Shaikh
Author-email: arifshaikh.astro@gmail.com
License: MIT
Project-URL: Bug Tracker, https://github.com/md-arif-shaikh/ycv/issues
Classifier: Programming Language :: Python :: 3
Classifier: Operating System :: OS Independent
Requires-Python: >=3.7
License-File: LICENSE
Requires-Dist: pyyaml
Requires-Dist: bibtexparser
Dynamic: license-file
